Metadata-Version: 2.4
Name: weather-mcp-yethu
Version: 0.1.1
Summary: Add your description here
Requires-Python: >=3.13
Requires-Dist: build>=1.2.2.post1
Requires-Dist: langchain-google-genai>=2.1.3
Requires-Dist: langchain-mcp-adapters>=0.0.9
Requires-Dist: langchain-openai>=0.3.14
Requires-Dist: langgraph>=0.3.31
Requires-Dist: mcp[cli]>=1.6.0
